{
  "name": "Multi-Asset RSI & MA Crossover Alerts",
  "nodes": [
    {
      "parameters": {
        "rule": {
          "interval": [
            {
              "triggerAtHour": 9
            }
          ]
        }
      },
      "type": "n8n-nodes-base.scheduleTrigger",
      "typeVersion": 1.3,
      "position": [
        -400,
        176
      ],
      "id": "fec822d2-b2e7-4a2e-b329-afa340a04be5",
      "name": "Schedule Trigger"
    },
    {
      "parameters": {
        "mode": "raw",
        "jsonOutput": "{\n  \"symbols\": [\"AAPL\", \"TSLA\", \"MSFT\"]\n}\n",
        "options": {}
      },
      "type": "n8n-nodes-base.set",
      "typeVersion": 3.4,
      "position": [
        -192,
        176
      ],
      "id": "696dbfe5-d1e3-45fc-a80d-255e9972ef9c",
      "name": "Watchlist"
    },
    {
      "parameters": {
        "numberInputs": 3
      },
      "type": "n8n-nodes-base.merge",
      "typeVersion": 3.2,
      "position": [
        192,
        160
      ],
      "id": "95e38ccf-34fa-4667-9d79-03e773596922",
      "name": "Merge"
    },
    {
      "parameters": {
        "jsCode": "// Ambil semua item hasil merge\nconst results = items.map(item => item.json);\n\n// Helper functions\nfunction SMA(data, period) {\n  return data.map((_, i, arr) => {\n    if (i < period) return null;\n    const slice = arr.slice(i - period, i);\n    return slice.reduce((a, b) => a + b, 0) / period;\n  });\n}\n\nfunction RSI(data, period = 14) {\n  const gains = [], losses = [];\n  for (let i = 1; i < data.length; i++) {\n    const diff = data[i] - data[i - 1];\n    gains.push(diff > 0 ? diff : 0);\n    losses.push(diff < 0 ? -diff : 0);\n  }\n  if (gains.length < period) return null;\n  let avgGain = gains.slice(0, period).reduce((a,b)=>a+b,0)/period;\n  let avgLoss = losses.slice(0, period).reduce((a,b)=>a+b,0)/period;\n  for (let i = period; i < gains.length; i++) {\n    avgGain = (avgGain * (period - 1) + gains[i]) / period;\n    avgLoss = (avgLoss * (period - 1) + losses[i]) / period;\n  }\n  const rs = avgGain / (avgLoss || 1);\n  return 100 - 100 / (1 + rs);\n}\n\nconst output = [];\n\nfor (const data of results) {\n  try {\n    // result adalah chart.result[0] jika ada\n    const result = data.chart?.result?.[0];\n\n    // > SKIP jika tidak ada chart/result\n    if (!result) {\n      output.push({ json: { error: 'No chart/result for one item', raw: data } });\n      continue;\n    }\n\n    // Symbol seharusnya ada di result.meta.symbol (Yahoo)\n    const symbol = result.meta?.symbol || data.symbol || data.meta?.symbol || 'UNKNOWN';\n\n    // Dapatkan closes, safety checks\n    const closesRaw = result.indicators?.quote?.[0]?.close;\n    if (!closesRaw || !Array.isArray(closesRaw)) {\n      output.push({ json: { symbol, error: 'No close prices in response' } });\n      continue;\n    }\n    const closes = closesRaw.filter(v => v !== null && v !== undefined);\n\n    // Pastikan cukup data untuk MA200; kalau tidak, beri flag\n    if (closes.length < 50) {\n      output.push({ json: { symbol, error: 'Not enough candles', candles: closes.length } });\n      continue;\n    }\n\n    // Hitung indikator\n    const ma50 = SMA(closes, 50);\n    const ma200 = SMA(closes, 200);\n    const lastClose = closes.at(-1);\n    const lastMA50 = ma50.filter(v => v !== null).at(-1) || null;\n    const lastMA200 = ma200.filter(v => v !== null).at(-1) || null;\n    const rsi = RSI(closes, 14);\n\n    // Tentukan sinyal (prioritas RSI dulu)\n    let signal = '⚪ Tidak ada sinyal saat ini';\n    if (rsi !== null && rsi < 30) signal = '🔵 RSI Oversold (Potensi Buy)';\n    else if (rsi !== null && rsi > 70) signal = '🔴 RSI Overbought (Potensi Sell)';\n    else if (lastMA50 !== null && lastMA200 !== null && lastMA50 > lastMA200) signal = '🟢 Golden Cross (Buy Signal)';\n    else if (lastMA50 !== null && lastMA200 !== null && lastMA50 < lastMA200) signal = '🔻 Death Cross (Sell Signal)';\n\n    output.push({\n      json: {\n        symbol,\n        lastClose,\n        rsi: rsi !== null ? Number(rsi.toFixed(2)) : null,\n        ma50: lastMA50 !== null ? Number(lastMA50.toFixed(2)) : null,\n        ma200: lastMA200 !== null ? Number(lastMA200.toFixed(2)) : null,\n        signal\n      }\n    });\n  } catch (err) {\n    output.push({ json: { error: err.message } });\n  }\n}\n\nreturn output;"
      },
      "type": "n8n-nodes-base.code",
      "typeVersion": 2,
      "position": [
        384,
        176
      ],
      "id": "11916b11-cde3-47c2-b4bb-d6ed8a501dfc",
      "name": "Anayze Signals"
    },
    {
      "parameters": {
        "chatId": "1564368734",
        "text": "=📊 Symbol: {{$json[\"symbol\"]}}\n\n💰 Harga terakhir: {{$json[\"lastClose\"]}}\n📈 RSI: {{$json[\"rsi\"]}}\n📊 MA50: {{$json[\"ma50\"]}}\n📊 MA200: {{$json[\"ma200\"]}}\n\n🚨 Sinyal: {{$json[\"signal\"]}}",
        "additionalFields": {}
      },
      "type": "n8n-nodes-base.telegram",
      "typeVersion": 1.2,
      "position": [
        592,
        176
      ],
      "id": "7b6f1f9c-c748-48c7-a7b2-e5ef5ee78418",
      "name": "Kirim Pesan ke Tele (Stocks)",
      "webhookId": "01a0d635-281c-4a08-b97d-4654f6ba71d5",
      "credentials": {
        "telegramApi": {
          "id": "g18uN5UdGv6IWagT",
          "name": "Telegram account"
        }
      }
    },
    {
      "parameters": {
        "rule": {
          "interval": [
            {}
          ]
        }
      },
      "type": "n8n-nodes-base.scheduleTrigger",
      "typeVersion": 1.3,
      "position": [
        -288,
        592
      ],
      "id": "8d7eb759-5b57-440d-a2dd-613260cccc6c",
      "name": "Schedule Trigger1"
    },
    {
      "parameters": {
        "url": "=https://query1.finance.yahoo.com/v8/finance/chart/BTC-USD",
        "sendQuery": true,
        "queryParameters": {
          "parameters": [
            {
              "name": "range",
              "value": "1d"
            },
            {
              "name": "interval",
              "value": "5m"
            }
          ]
        },
        "sendHeaders": true,
        "headerParameters": {
          "parameters": [
            {
              "name": "User-Agent",
              "value": "Mozilla/5.0"
            },
            {
              "name": "Accept",
              "value": "application/json"
            }
          ]
        },
        "options": {}
      },
      "type": "n8n-nodes-base.httpRequest",
      "typeVersion": 4.4,
      "position": [
        -80,
        592
      ],
      "id": "837c76d8-7e4e-4a6c-99c0-a5a9fa477b4d",
      "name": "BTC/USD"
    },
    {
      "parameters": {
        "chatId": "1564368734",
        "text": "=📊 [BTC-USD] Sinyal 5m\n\n💰 Harga terakhir: {{$json[\"lastClose\"]}}\n📈 RSI: {{$json[\"rsi\"]}}\n📊 MA50: {{$json[\"ma50\"]}}\n📊 MA200: {{$json[\"ma200\"]}}\n\n🚨 Sinyal: {{$json[\"signal\"]}}",
        "additionalFields": {}
      },
      "type": "n8n-nodes-base.telegram",
      "typeVersion": 1.2,
      "position": [
        336,
        592
      ],
      "id": "33ef2343-0cf7-4851-b51c-1b2d2475bce2",
      "name": "Kirim Pesan ke Tele (BTC)",
      "webhookId": "44fd30da-4006-4da0-8279-89d79aa05d0b",
      "credentials": {
        "telegramApi": {
          "id": "g18uN5UdGv6IWagT",
          "name": "Telegram account"
        }
      }
    },
    {
      "parameters": {
        "jsCode": "// === Ambil data harga dari Yahoo Finance ===\nconst data = items[0].json.chart?.result?.[0];\nif (!data) {\n  return [{ json: { error: \"❌ Tidak ada data dari Yahoo Finance.\" } }];\n}\n\nconst closes = data.indicators.quote[0].close.filter(v => v !== null);\n\n// === Fungsi bantu ===\nfunction SMA(data, period) {\n  return data.map((_, i, arr) => {\n    if (i < period) return null;\n    const slice = arr.slice(i - period, i);\n    return slice.reduce((a, b) => a + b, 0) / period;\n  });\n}\n\nfunction RSI(data, period = 14) {\n  let gains = [], losses = [];\n  for (let i = 1; i < data.length; i++) {\n    const diff = data[i] - data[i - 1];\n    gains.push(diff > 0 ? diff : 0);\n    losses.push(diff < 0 ? -diff : 0);\n  }\n\n  if (gains.length < period) return null;\n\n  let avgGain = gains.slice(0, period).reduce((a, b) => a + b, 0) / period;\n  let avgLoss = losses.slice(0, period).reduce((a, b) => a + b, 0) / period;\n\n  for (let i = period; i < gains.length; i++) {\n    avgGain = (avgGain * (period - 1) + gains[i]) / period;\n    avgLoss = (avgLoss * (period - 1) + losses[i]) / period;\n  }\n\n  const rs = avgGain / (avgLoss || 1);\n  return 100 - 100 / (1 + rs);\n}\n\n// === Hitung indikator ===\nconst ma50 = SMA(closes, 50);\nconst ma200 = SMA(closes, 200);\n\nconst lastClose = closes.at(-1);\nconst lastMA50 = ma50.at(-1);\nconst lastMA200 = ma200.filter(v => v !== null).at(-1) || lastMA50;\nconst rsi = RSI(closes, 14);\n\n// === Tentukan sinyal ===\nlet signal = \"⚪ Tidak ada sinyal saat ini\";\nif (rsi && rsi < 30) signal = \"🔵 RSI Oversold (Potensi Buy)\";\nelse if (rsi && rsi > 70) signal = \"🔴 RSI Overbought (Potensi Sell)\";\nelse if (lastMA50 > lastMA200) signal = \"🟢 Golden Cross (Buy Signal)\";\nelse if (lastMA50 < lastMA200) signal = \"🔻 Death Cross (Sell Signal)\";\n\n// === Return hasil ===\nreturn [{\n  json: {\n    symbol: data.meta.symbol || \"BTC-USD\",\n    lastClose,\n    rsi: rsi ? rsi.toFixed(2) : null,\n    ma50: lastMA50 ? lastMA50.toFixed(2) : null,\n    ma200: lastMA200 ? lastMA200.toFixed(2) : null,\n    signal\n  }\n}];"
      },
      "type": "n8n-nodes-base.code",
      "typeVersion": 2,
      "position": [
        128,
        592
      ],
      "id": "a205b233-e286-48f8-88ca-6aad9ac5dee4",
      "name": "Analyze Signal BTC"
    },
    {
      "parameters": {
        "url": "={{ `https://query1.finance.yahoo.com/v8/finance/chart/${$json.symbols[0]}` }}",
        "sendQuery": true,
        "queryParameters": {
          "parameters": [
            {
              "name": "range",
              "value": "6mo"
            },
            {
              "name": "interval",
              "value": "1d"
            }
          ]
        },
        "sendHeaders": true,
        "headerParameters": {
          "parameters": [
            {
              "name": "User-Agent",
              "value": "Mozilla/5.0"
            },
            {
              "name": "Accept",
              "value": "application/json"
            }
          ]
        },
        "options": {}
      },
      "type": "n8n-nodes-base.httpRequest",
      "typeVersion": 4.4,
      "position": [
        0,
        0
      ],
      "id": "fe23b359-190f-4dd5-85df-730ec6360922",
      "name": "AAPL"
    },
    {
      "parameters": {
        "url": "={{ `https://query1.finance.yahoo.com/v8/finance/chart/${$json.symbols[1]}` }}",
        "sendQuery": true,
        "queryParameters": {
          "parameters": [
            {
              "name": "range",
              "value": "6mo"
            },
            {
              "name": "interval",
              "value": "1d"
            }
          ]
        },
        "sendHeaders": true,
        "headerParameters": {
          "parameters": [
            {
              "name": "User-Agent",
              "value": "Mozilla/5.0"
            },
            {
              "name": "Accept",
              "value": "application/json"
            }
          ]
        },
        "options": {}
      },
      "type": "n8n-nodes-base.httpRequest",
      "typeVersion": 4.4,
      "position": [
        0,
        176
      ],
      "id": "607a8174-e850-4220-be36-7471945334db",
      "name": "TSLA"
    },
    {
      "parameters": {
        "url": "={{ `https://query1.finance.yahoo.com/v8/finance/chart/${$json.symbols[2]}` }}",
        "sendQuery": true,
        "queryParameters": {
          "parameters": [
            {
              "name": "range",
              "value": "6mo"
            },
            {
              "name": "interval",
              "value": "1d"
            }
          ]
        },
        "sendHeaders": true,
        "headerParameters": {
          "parameters": [
            {
              "name": "User-Agent",
              "value": "Mozilla/5.0"
            },
            {
              "name": "Accept",
              "value": "application/json"
            }
          ]
        },
        "options": {}
      },
      "type": "n8n-nodes-base.httpRequest",
      "typeVersion": 4.4,
      "position": [
        0,
        368
      ],
      "id": "52b9965e-452e-4687-9577-1cbeac15b64a",
      "name": "MSFT"
    }
  ],
  "pinData": {},
  "connections": {
    "Schedule Trigger": {
      "main": [
        [
          {
            "node": "Watchlist",
            "type": "main",
            "index": 0
          }
        ]
      ]
    },
    "Watchlist": {
      "main": [
        [
          {
            "node": "AAPL",
            "type": "main",
            "index": 0
          },
          {
            "node": "TSLA",
            "type": "main",
            "index": 0
          },
          {
            "node": "MSFT",
            "type": "main",
            "index": 0
          }
        ]
      ]
    },
    "Merge": {
      "main": [
        [
          {
            "node": "Anayze Signals",
            "type": "main",
            "index": 0
          }
        ]
      ]
    },
    "Anayze Signals": {
      "main": [
        [
          {
            "node": "Kirim Pesan ke Tele (Stocks)",
            "type": "main",
            "index": 0
          }
        ]
      ]
    },
    "Schedule Trigger1": {
      "main": [
        [
          {
            "node": "BTC/USD",
            "type": "main",
            "index": 0
          }
        ]
      ]
    },
    "BTC/USD": {
      "main": [
        [
          {
            "node": "Analyze Signal BTC",
            "type": "main",
            "index": 0
          }
        ]
      ]
    },
    "Analyze Signal BTC": {
      "main": [
        [
          {
            "node": "Kirim Pesan ke Tele (BTC)",
            "type": "main",
            "index": 0
          }
        ]
      ]
    },
    "AAPL": {
      "main": [
        [
          {
            "node": "Merge",
            "type": "main",
            "index": 0
          }
        ]
      ]
    },
    "TSLA": {
      "main": [
        [
          {
            "node": "Merge",
            "type": "main",
            "index": 1
          }
        ]
      ]
    },
    "MSFT": {
      "main": [
        [
          {
            "node": "Merge",
            "type": "main",
            "index": 2
          }
        ]
      ]
    }
  },
  "active": false,
  "settings": {
    "executionOrder": "v1",
    "binaryMode": "separate"
  },
  "versionId": "fe070bbb-a401-4e88-8a7b-6c9c136bfb54",
  "meta": {
    "templateCredsSetupCompleted": true,
    "instanceId": "8cc0eeade57669f0b770595d75740d782dc713341b8717109d9eab32ed5f8f6b"
  },
  "id": "ezJRNGfeQ0Kepm0F",
  "tags": []
}